icecore/__init__.py
icecore/icecore.so
icecore/libICECrypt.so.0.2
icecore/libcryptopp.so.6.0
icecore-0.2.0.0.dist-info/DESCRIPTION.rst
icecore-0.2.0.0.dist-info/METADATA
icecore-0.2.0.0.dist-info/RECORD
icecore-0.2.0.0.dist-info/WHEEL
icecore-0.2.0.0.dist-info/metadata.json
icecore-0.2.0.0.dist-info/top_level.txt
